{
    "ConfigVersion": 28,
    "ID": 18,
    "Type": 11,
    "Title": "Crafting: Make Yourself a Fur Bag",
    "Descriptions": [
        "You're going to need some extra storage, might as well have some flare too, right? Make yourself a bag and I'll give you a little something to put in it. -Stinky Pete-",
        "Still working on it?",
        "Look at that..."
    ],
    "ObjectiveText": "Craft a Courier Bag",
    "FollowUpQuest": 0,
    "Repeatable": 0,
    "IsDailyQuest": 0,
    "IsWeeklyQuest": 0,
    "CancelQuestOnPlayerDeath": 0,
    "Autocomplete": 0,
    "IsGroupQuest": 0,
    "ObjectSetFileName": "",
    "QuestItems": [
        {
            "ClassName": "Rope",
            "Amount": 1,
            "Attachments": [],
            "DamagePercent": 0,
            "HealthPercent": 0,
            "QuestID": -1,
            "Chance": 1.0
        },
        {
            "ClassName": "BurlapSack",
            "Amount": 1,
            "Attachments": [],
            "DamagePercent": 0,
            "HealthPercent": 0,
            "QuestID": -1,
            "Chance": 1.0
        }
    ],
    "Rewards": [
        {
            "ClassName": "CanOpener",
            "Amount": 1,
            "Attachments": [],
            "DamagePercent": 0,
            "HealthPercent": 0,
            "QuestID": -1,
            "Chance": 1.0
        },
        {
            "ClassName": "TacticalBaconCan",
            "Amount": 1,
            "Attachments": [],
            "DamagePercent": 0,
            "HealthPercent": 0,
            "QuestID": -1,
            "Chance": 1.0
        },
        {
            "ClassName": "CourierBag",
            "Amount": 1,
            "Attachments": [],
            "DamagePercent": 0,
            "HealthPercent": 0,
            "QuestID": -1,
            "Chance": 1.0
        }
    ],
    "NeedToSelectReward": 1,
    "RandomReward": 0,
    "RandomRewardAmount": -1,
    "RewardsForGroupOwnerOnly": 1,
    "RewardBehavior": 0,
    "QuestGiverIDs": [
        1
    ],
    "QuestTurnInIDs": [
        1
    ],
    "IsAchievement": 0,
    "Objectives": [
        {
            "ConfigVersion": 28,
            "ID": 18,
            "ObjectiveType": 11
        }
    ],
    "QuestColor": 0,
    "ReputationReward": 0,
    "ReputationRequirement": -1,
    "PreQuestIDs": [
        17
    ],
    "RequiredFaction": "",
    "FactionReward": "",
    "PlayerNeedQuestItems": 1,
    "DeleteQuestItems": 0,
    "SequentialObjectives": 0,
    "FactionReputationRequirements": {},
    "FactionReputationRewards": {},
    "SuppressQuestLogOnCompetion": 0,
    "Active": 1
}